{
  "metadata": {
    "user": "AI Addict",
    "date": "2021-04-29",
    "location": "Silicon Valley",
    "fsd-version": "8.2 (2021.4.11.1)",
    "video-link": "https://www.youtube.com/watch?v=0e7TVCRQEcQ",
    "video-length": "10:26"
  },
  "events": [
    {"time": "0:37", "codes": ["D-C"]},
    {"time": "1:03", "codes": ["D-C"]},
    {"time": "1:28", "codes": ["I-SLOW"]},
    {"time": "1:35", "codes": ["D-C"]},
    {"time": "2:13", "codes": ["D-D"]},
    {"time": "2:33", "codes": ["I-SLOW"]},
    {"time": "3:09", "codes": ["W-RED"]},
    {"time": "4:01", "codes": ["W-DRUNK"]},
    {"time": "4:17", "codes": ["D-D"]},
    {"time": "5:09", "codes": ["W-YSLOW"]},
    {"time": "6:46", "codes": ["I-TURN"]},
    {"time": "9:02", "codes": ["W-DRUNK"]},
    {"time": "9:15", "codes": ["W-YSLOW"]}
  ]
}
